nopause/__init__.py
nopause/version.py
nopause/core/__init__.py
nopause/core/audio.py
nopause/core/base.py
nopause/sdk/__init__.py
nopause/sdk/base.py
nopause/sdk/config.py
nopause/sdk/error.py
nopause/sdk/synthesis.py
nopause/sdk/voice.py
nopause/utils/__init__.py
nopause/utils/timestamp.py
nopause-0.2.0.dist-info/LICENSE
nopause-0.2.0.dist-info/METADATA
nopause-0.2.0.dist-info/WHEEL
nopause-0.2.0.dist-info/top_level.txt
nopause-0.2.0.dist-info/zip-safe
nopause-0.2.0.dist-info/RECORD
