Metadata-Version: 2.1
Name: nopause
Version: 0.2.0
Summary: Python client SDK for the NoPause API
Home-page: https://github.com/nopause-io/nopause-python
Author: NoPause
Author-email: hellotts@nopause.com
Classifier: Programming Language :: Python :: 3
Classifier: License :: OSI Approved :: Apache Software License
Classifier: Operating System :: OS Independent
Requires-Python: >=3.7.1
License-File: LICENSE
Requires-Dist: websockets >=11.0.3
Requires-Dist: pydantic <2.0,>=1.10.6
Requires-Dist: ujson >=5.5.0
